panini/__init__.py
panini/drivers.py
panini/main.py
panini/utils.py
panini_compose-0.1.2.dist-info/licenses/LICENSE
panini_compose-0.1.2.dist-info/METADATA
panini_compose-0.1.2.dist-info/WHEEL
panini_compose-0.1.2.dist-info/entry_points.txt
panini_compose-0.1.2.dist-info/top_level.txt
panini_compose-0.1.2.dist-info/RECORD
